skytek_utils/VERSION
skytek_utils/__init__.py
skytek_utils/celery.py
skytek_utils/datetime.py
skytek_utils/files.py
skytek_utils/iter.py
skytek_utils/monitoring.py
skytek_utils/django/__init__.py
skytek_utils/django/forms.py
skytek_utils/django/materialized_views.py
skytek_utils/django/models.py
skytek_utils/django/shortcuts.py
skytek_utils/interconnect/__init__.py
skytek_utils/interconnect/api/__init__.py
skytek_utils/interconnect/api/authentication.py
skytek_utils/interconnect/api/client.py
skytek_utils/interconnect/api/conf.py
skytek_utils/interconnect/api/jwt.py
skytek_utils/interconnect/api/mixins.py
skytek_utils/interconnect/api/permissions.py
skytek_utils/interconnect/api/user.py
skytek_utils/spatial/__init__.py
skytek_utils/spatial/tiles.py
skytek_utils-0.10.0.dist-info/LICENSE
skytek_utils-0.10.0.dist-info/METADATA
skytek_utils-0.10.0.dist-info/WHEEL
skytek_utils-0.10.0.dist-info/top_level.txt
skytek_utils-0.10.0.dist-info/RECORD
