Metadata-Version: 2.1
Name: skytek-utils
Version: 0.10.0
Summary: skytek-utils - a set of small util functions
Home-page: http://github.com/Skytek/skytek-utils
Author: Skytek Ltd.
Author-email: wiktor.latanowicz@skytek.com
License: LGPLv3
Classifier: Programming Language :: Python :: 3.9
Classifier: License :: OSI Approved :: GNU Lesser General Public License v3 (LGPLv3)
Classifier: Operating System :: OS Independent
Requires-Python: >=3.9
License-File: LICENSE
Requires-Dist: django >=3.2.0
Requires-Dist: ddtrace >=1.1.3
Requires-Dist: datadog >=0.44.0
Requires-Dist: celery >=5.2
Requires-Dist: python-dateutil >=2.8.2
Requires-Dist: PyJWT >=2.6.0
Requires-Dist: djangorestframework >=3.14
